enthusiast_model_openai/__init__.py
enthusiast_model_openai/embedding.py
enthusiast_model_openai/language_model.py
enthusiast_model_openai-1.3.0.dist-info/METADATA
enthusiast_model_openai-1.3.0.dist-info/WHEEL
enthusiast_model_openai-1.3.0.dist-info/RECORD
