Metadata-Version: 2.4
Name: enthusiast-model-openai
Version: 1.3.0
Summary: A plugin for Enthusiast that provides an OpenAI connector.
Author: Rafal Cymerys
Author-email: rafal@upsidelab.io
Requires-Python: >=3.10,<4.0
Classifier: Programming Language :: Python :: 3
Classifier: Programming Language :: Python :: 3.10
Classifier: Programming Language :: Python :: 3.11
Classifier: Programming Language :: Python :: 3.12
Classifier: Programming Language :: Python :: 3.13
Classifier: Programming Language :: Python :: 3.14
Requires-Dist: enthusiast-common (>=1,<2)
Requires-Dist: langchain-core (>=0.3.66,<0.4.0)
Requires-Dist: langchain-openai (>=0.3.27,<0.4.0)
Requires-Dist: openai (>=1.86.0,<2.0.0)
